ksecret/__init__.py
ksecret/cli.py
ksecret-0.1.0.post1.dist-info/licenses/LICENSE
ksecret-0.1.0.post1.dist-info/METADATA
ksecret-0.1.0.post1.dist-info/WHEEL
ksecret-0.1.0.post1.dist-info/entry_points.txt
ksecret-0.1.0.post1.dist-info/top_level.txt
ksecret-0.1.0.post1.dist-info/RECORD
