Metadata-Version: 2.4
Name: ksecret
Version: 0.1.0.post1
Summary: A Kubernetes Secret Helper
Author-email: hikari <me@metantesan.com>
License: BSD 3-Clause License
Requires-Python: >=3.13
License-File: LICENSE
Requires-Dist: pyyaml>=6.0.2
Requires-Dist: rich>=14.0.0
Requires-Dist: rich-click>=1.8.9
Dynamic: license-file
